laser_encoders/README.md
laser_encoders/__init__.py
laser_encoders/download_models.py
laser_encoders/language_list.py
laser_encoders/laser_tokenizer.py
laser_encoders/models.py
laser_encoders/test_laser_tokenizer.py
laser_encoders/test_models_initialization.py
laser_encoders/validate_models.py
laser_encoders-0.0.2.dist-info/WHEEL
laser_encoders-0.0.2.dist-info/METADATA
laser_encoders-0.0.2.dist-info/RECORD
