Metadata-Version: 2.1
Name: laser_encoders
Version: 0.0.2
Summary: LASER  Language-Agnostic SEntence Representations is a toolkit to calculate multilingual sentence embeddings and to use them for document classification, bitext filtering and mining
Author: Facebook AI Research
Requires-Python: >=3.8
Classifier: License :: OSI Approved :: BSD License
Classifier: Topic :: Scientific/Engineering
Classifier: Development Status :: 4 - Beta
Requires-Dist: sacremoses==0.1.0
Requires-Dist: unicategories>=0.1.2
Requires-Dist: sentencepiece>=0.1.99
Requires-Dist: numpy>=1.21.3
Requires-Dist: torch>=1.10.0
Requires-Dist: fairseq>=0.12.2
Requires-Dist: pytest>=4.3.0 ; extra == "dev"
Requires-Dist: black==22.3.0 ; extra == "dev"
Requires-Dist: isort>=5.10.1 ; extra == "dev"
Requires-Dist: mypy>=0.782 ; extra == "dev"
Requires-Dist: pylint>=2.8.0 ; extra == "dev"
Requires-Dist: flit>=3.5.1 ; extra == "dev"
Project-URL: Bug Tracker, https://github.com/facebookresearch/LASER/issues
Project-URL: Homepage, https://github.com/facebookresearch/LASER
Provides-Extra: dev
